odoo10_addon_partner_external_map-10.0.1.0.0-py2.7-nspkg.pth
odoo10_addon_partner_external_map-10.0.1.0.0.dist-info/top_level.txt
odoo10_addon_partner_external_map-10.0.1.0.0.dist-info/WHEEL
odoo10_addon_partner_external_map-10.0.1.0.0.dist-info/RECORD
odoo10_addon_partner_external_map-10.0.1.0.0.dist-info/metadata.json
odoo10_addon_partner_external_map-10.0.1.0.0.dist-info/DESCRIPTION.rst
odoo10_addon_partner_external_map-10.0.1.0.0.dist-info/METADATA
odoo10_addon_partner_external_map-10.0.1.0.0.dist-info/namespace_packages.txt
odoo/addons/partner_external_map/__manifest__.py
odoo/addons/partner_external_map/hooks.py
odoo/addons/partner_external_map/__init__.py
odoo/addons/partner_external_map/README.rst
odoo/addons/partner_external_map/security/ir.model.access.csv
odoo/addons/partner_external_map/models/res_partner.py
odoo/addons/partner_external_map/models/__init__.py
odoo/addons/partner_external_map/models/map_website.py
odoo/addons/partner_external_map/models/res_users.py
odoo/addons/partner_external_map/i18n/pt.po
odoo/addons/partner_external_map/i18n/it.po
odoo/addons/partner_external_map/i18n/es.po
odoo/addons/partner_external_map/i18n/tr.po
odoo/addons/partner_external_map/i18n/gl.po
odoo/addons/partner_external_map/i18n/ca.po
odoo/addons/partner_external_map/i18n/sl.po
odoo/addons/partner_external_map/i18n/es_ES.po
odoo/addons/partner_external_map/i18n/pt_PT.po
odoo/addons/partner_external_map/i18n/da.po
odoo/addons/partner_external_map/i18n/nl.po
odoo/addons/partner_external_map/i18n/am.po
odoo/addons/partner_external_map/i18n/de.po
odoo/addons/partner_external_map/i18n/fr.po
odoo/addons/partner_external_map/i18n/pt_BR.po
odoo/addons/partner_external_map/i18n/el_GR.po
odoo/addons/partner_external_map/i18n/fi.po
odoo/addons/partner_external_map/i18n/hr_HR.po
odoo/addons/partner_external_map/views/res_partner_view.xml
odoo/addons/partner_external_map/views/map_website_view.xml
odoo/addons/partner_external_map/views/res_users_view.xml
odoo/addons/partner_external_map/data/map_website_data.xml
odoo/addons/partner_external_map/tests/test_partner_external_map.py
odoo/addons/partner_external_map/tests/__init__.py
odoo/addons/partner_external_map/static/description/icon.svg
odoo/addons/partner_external_map/static/description/icon.png
