Metadata-Version: 2.0
Name: odoo10-addon-partner-external-map
Version: 10.0.1.0.0
Summary: Add Map and Map Routing buttons on partner form to open GMaps, OSM, Bing and others
Home-page: http://www.akretion.com
Author: UNKNOWN
Author-email: UNKNOWN
License: AGPL-3
Platform: UNKNOWN
Requires-Dist: odoo (<10.1dev,>=10.0)
Classifier: Programming Language :: Python :: 2.7
Classifier: Framework :: Odoo
Classifier: License :: OSI Approved :: GNU Affero General Public License v3
